[{"class_name": "collapsed", "bbox": "1 190 103 302", "used": true}, {"class_name": "collapsed", "bbox": "96 297 159 357", "used": true}, {"class_name": "collapsed", "bbox": "8 338 55 387", "used": true}, {"class_name": "collapsed", "bbox": "130 386 168 417", "used": false}, {"class_name": "collapsed", "bbox": "263 334 308 396", "used": true}, {"class_name": "collapsed", "bbox": "275 279 321 323", "used": true}, {"class_name": "collapsed", "bbox": "192 177 280 269", "used": true}, {"class_name": "collapsed", "bbox": "263 178 361 287", "used": true}, {"class_name": "collapsed", "bbox": "367 139 405 181", "used": true}, {"class_name": "collapsed", "bbox": "208 39 259 90", "used": true}]